questplus/__init__.py
questplus/_constants.py
questplus/psychometric_function.py
questplus/qp.py
questplus/utils.py
questplus/tests/test_qp.py
questplus-2023.1.dist-info/AUTHORS
questplus-2023.1.dist-info/LICENSE
questplus-2023.1.dist-info/METADATA
questplus-2023.1.dist-info/WHEEL
questplus-2023.1.dist-info/top_level.txt
questplus-2023.1.dist-info/RECORD
