Metadata-Version: 2.1
Name: questplus
Version: 2023.1
Summary: A QUEST+ implementation in Python.
Author: Richard Höchenberger
Author-email: richard.hoechenberger@gmail.com
License:                     GNU GENERAL PUBLIC LICENSE
Keywords: science,neuroscience,psychology,staircase
Classifier: Intended Audience :: Science/Research
Classifier: Programming Language :: Python
Requires-Python: >=3.8
License-File: LICENSE
License-File: AUTHORS
